CHANGES.txt
LICENSE.txt
MANIFEST.in
README.rst
setup.py
SpotiCLI.egg-info/PKG-INFO
SpotiCLI.egg-info/SOURCES.txt
SpotiCLI.egg-info/dependency_links.txt
SpotiCLI.egg-info/entry_points.txt
SpotiCLI.egg-info/requires.txt
SpotiCLI.egg-info/top_level.txt
spoticli/__init__.py
spoticli/getch.py
spoticli/listcreator.py
spoticli/spotify_cli.py
spoticli/version.py