Metadata-Version: 1.0
Name: SpotiCLI
Version: 0.1.1
Summary: control Spotify from the command line
Home-page: https://github.com/justinawrey/spotiCLI
Author: justinawrey
Author-email: awreyjustin@gmail.com
License: LICENSE.txt
Keywords: spotify command line interface controller
Platform: UNKNOWN
